codegraphcontext/__init__.py
codegraphcontext/__main__.py
codegraphcontext/prompts.py
codegraphcontext/server.py
codegraphcontext/tool_definitions.py
codegraphcontext/cli/__init__.py
codegraphcontext/cli/cli_helpers.py
codegraphcontext/cli/config_manager.py
codegraphcontext/cli/main.py
codegraphcontext/cli/registry_commands.py
codegraphcontext/cli/setup_macos.py
codegraphcontext/cli/setup_wizard.py
codegraphcontext/cli/visualizer.py
codegraphcontext/core/__init__.py
codegraphcontext/core/cgc_bundle.py
codegraphcontext/core/database.py
codegraphcontext/core/database_falkordb.py
codegraphcontext/core/falkor_worker.py
codegraphcontext/core/jobs.py
codegraphcontext/core/watcher.py
codegraphcontext/tools/__init__.py
codegraphcontext/tools/advanced_language_query_tool.py
codegraphcontext/tools/code_finder.py
codegraphcontext/tools/graph_builder.py
codegraphcontext/tools/package_resolver.py
codegraphcontext/tools/system.py
codegraphcontext/tools/handlers/analysis_handlers.py
codegraphcontext/tools/handlers/indexing_handlers.py
codegraphcontext/tools/handlers/management_handlers.py
codegraphcontext/tools/handlers/query_handlers.py
codegraphcontext/tools/handlers/watcher_handlers.py
codegraphcontext/tools/languages/c.py
codegraphcontext/tools/languages/cpp.py
codegraphcontext/tools/languages/csharp.py
codegraphcontext/tools/languages/go.py
codegraphcontext/tools/languages/haskell.py
codegraphcontext/tools/languages/java.py
codegraphcontext/tools/languages/javascript.py
codegraphcontext/tools/languages/kotlin.py
codegraphcontext/tools/languages/php.py
codegraphcontext/tools/languages/python.py
codegraphcontext/tools/languages/ruby.py
codegraphcontext/tools/languages/rust.py
codegraphcontext/tools/languages/scala.py
codegraphcontext/tools/languages/swift.py
codegraphcontext/tools/languages/typescript.py
codegraphcontext/tools/languages/typescriptjsx.py
codegraphcontext/tools/query_tool_languages/c_toolkit.py
codegraphcontext/tools/query_tool_languages/cpp_toolkit.py
codegraphcontext-0.1.41.dist-info/licenses/LICENSE
codegraphcontext-0.1.41.dist-info/METADATA
codegraphcontext-0.1.41.dist-info/WHEEL
codegraphcontext-0.1.41.dist-info/entry_points.txt
codegraphcontext-0.1.41.dist-info/top_level.txt
codegraphcontext-0.1.41.dist-info/RECORD
