Metadata-Version: 2.4
Name: codegraphcontext
Version: 0.1.41
Summary: An MCP server that indexes local code into a graph database to provide context to AI assistants.
Author-email: Shashank Shekhar Singh <shashankshekharsingh1205@gmail.com>
License: MIT License
Project-URL: Homepage, https://github.com/Shashankss1205/CodeGraphContext
Project-URL: Bug Tracker, https://github.com/Shashankss1205/CodeGraphContext/issues
Classifier: Programming Language :: Python :: 3
Classifier: License :: OSI Approved :: MIT License
Classifier: Operating System :: OS Independent
Classifier: Development Status :: 3 - Alpha
Classifier: Intended Audience :: Developers
Classifier: Topic :: Software Development :: Libraries :: Application Frameworks
Requires-Python: >=3.10
License-File: LICENSE
Requires-Dist: neo4j>=5.15.0
Requires-Dist: watchdog>=3.0.0
Requires-Dist: stdlibs>=2023.11.18
Requires-Dist: typer[all]>=0.9.0
Requires-Dist: rich>=13.7.0
Requires-Dist: inquirerpy>=0.3.4
Requires-Dist: python-dotenv>=1.0.0
Requires-Dist: tree-sitter>=0.21.0
Requires-Dist: tree-sitter-language-pack>=0.6.0
Requires-Dist: pyyaml
Requires-Dist: pytest
Requires-Dist: nbformat
Requires-Dist: nbconvert>=7.16.6
Requires-Dist: pathspec>=0.12.1
Requires-Dist: falkordblite>=0.1.0; sys_platform != "win32" and python_version >= "3.12"
Provides-Extra: parsing
Requires-Dist: tree-sitter>=0.21.0; extra == "parsing"
Requires-Dist: tree-sitter-language-pack>=0.6.0; extra == "parsing"
Provides-Extra: dev
Requires-Dist: pytest>=7.4.0; extra == "dev"
Requires-Dist: black>=23.11.0; extra == "dev"
Requires-Dist: pytest-asyncio>=0.21.0; extra == "dev"
Dynamic: license-file
